Metadata-Version: 2.1
Name: beefish3
Version: 0.1
Requires-Dist: pycryptodome
